NRWAL/__init__.py
NRWAL/version.py
NRWAL/analysis_library/hydrogen/electrolyzer_costs_eos.yaml
NRWAL/analysis_library/hydrogen/electrolyzer_costs_flat.yaml
NRWAL/analysis_library/hydrogen/pipeline.yaml
NRWAL/analysis_library/hydrogen/production_costs.yaml
NRWAL/analysis_library/hydrogen/production_curve.yaml
NRWAL/analysis_library/hydrogen/production_rate.yaml
NRWAL/analysis_library/hydrogen/water.yaml
NRWAL/analysis_library/marine_energy/bos.yaml
NRWAL/analysis_library/marine_energy/device.yaml
NRWAL/analysis_library/marine_energy/electrical.yaml
NRWAL/analysis_library/marine_energy/om.yaml
NRWAL/analysis_library/marine_energy/variables.yaml
NRWAL/analysis_library/osw_2015/array.yaml
NRWAL/analysis_library/osw_2015/cost_reductions.yaml
NRWAL/analysis_library/osw_2015/export.yaml
NRWAL/analysis_library/osw_2015/fixed.yaml
NRWAL/analysis_library/osw_2015/floating.yaml
NRWAL/analysis_library/osw_2015/grid.yaml
NRWAL/analysis_library/osw_2015/jacket.yaml
NRWAL/analysis_library/osw_2015/losses.yaml
NRWAL/analysis_library/osw_2015/maintenance.yaml
NRWAL/analysis_library/osw_2015/monopile.yaml
NRWAL/analysis_library/osw_2015/semi.yaml
NRWAL/analysis_library/osw_2015/spar.yaml
NRWAL/analysis_library/osw_2015/turbine.yaml
NRWAL/analysis_library/osw_2015/turbine_install.yaml
NRWAL/analysis_library/osw_2015/variables.yaml
NRWAL/analysis_library/osw_2019/cost_reductions.yaml
NRWAL/analysis_library/osw_2019/export.yaml
NRWAL/analysis_library/osw_2019/jacket.yaml
NRWAL/analysis_library/osw_2019/monopile.yaml
NRWAL/analysis_library/osw_2019/semi.yaml
NRWAL/analysis_library/osw_2019/spar.yaml
NRWAL/analysis_library/osw_2019/turbine.yaml
NRWAL/analysis_library/osw_2019/turbine_install.yaml
NRWAL/analysis_library/osw_2019/variables.yaml
NRWAL/analysis_library/osw_2022/array_updates_2022.yaml
NRWAL/analysis_library/osw_2022/cost_reductions_updates_2022.yaml
NRWAL/analysis_library/osw_2022/export_updates_2022.yaml
NRWAL/analysis_library/osw_2022/fb_maintenance_updates_2022.yaml
NREL_NRWAL-0.0.11.dist-info/LICENSE
NREL_NRWAL-0.0.11.dist-info/METADATA
NREL_NRWAL-0.0.11.dist-info/WHEEL
NREL_NRWAL-0.0.11.dist-info/entry_points.txt
NREL_NRWAL-0.0.11.dist-info/top_level.txt
NREL_NRWAL-0.0.11.dist-info/RECORD
