Metadata-Version: 2.1
Name: NREL-NRWAL
Version: 0.0.11
Summary: National Renewable Energy Laboratory's (NREL's) Wind AnalysisLibrary: NRWAL
Home-page: https://nrel.github.io/NRWAL/
Author: Jacob Nunemaker
Author-email: jacob.nunemaker@nrel.gov
License: BSD 3-Clause
Keywords: NRWAL
Platform: UNKNOWN
Classifier: Development Status :: 4 - Beta
Classifier: Intended Audience :: Science/Research
Classifier: License :: OSI Approved :: BSD License
Classifier: Natural Language :: English
Classifier: Programming Language :: Python :: 3.7
Classifier: Programming Language :: Python :: 3.8
Classifier: Programming Language :: Python :: 3.9
Requires-Python: >=3.7
License-File: LICENSE
Requires-Dist: click (>=7.0)
Requires-Dist: numpy (>=1.16)
Requires-Dist: pandas (>=1.0)
Requires-Dist: PyYAML
Provides-Extra: dev
Requires-Dist: pytest (>=5.2) ; extra == 'dev'
Requires-Dist: flake8 ; extra == 'dev'
Requires-Dist: pre-commit ; extra == 'dev'
Requires-Dist: pylint ; extra == 'dev'
Provides-Extra: test
Requires-Dist: pytest (>=5.2) ; extra == 'test'
